{"post_board": "Food", "post_id": "M.1589649619.A.DFC", "post_time": 1589649619, "post_title": "[食記] 台北 越南百年老店飛機河粉，北車新開幕", "post_author": "minglong1985", "post_body": "餐廳名稱：飛機河粉(新光站前店)\n   消費時間：2020年/5月\n   地址：台北市中正區忠孝西路一段66號B1\n   電話：(02) 6617-3788\n   營業時間：11:00–21:30\n\n網誌圖文版:https://www.tony60533.com/airplane-pho\n\n上次去北車新光三越地下街覓食，突然發現這間飛機河粉\n\n本人很愛吃河粉，看到有咖哩河粉整個超有興趣，就點來吃看看\n\n邊吃邊跟朋友討論說這間很好吃欸，不知道哪邊有分店\n\nGoogle之後才發現，原來我去的那天是新光站前店剛開幕第一天欸，也太幸運了吧\n\n重點是開幕前三天竟然有河粉買一送一，但要穿綠衣服才有，機車我穿灰色啦可惡\n\n目前飛機河粉有四間分店，台北除了北車新光外，還有101也有歐\n\n北車新光三越地下街的環境其實還滿不錯的耶，乾淨明亮\n\n重點因為疫情關係座位幾乎都有了隔板，都變成單人座為了很酷\n\n\n菜單在這，飛機河粉有三種口味，分別是傳統、酸辣、咖哩三種\n\n可以搭配套餐，有套餐A+60元，套餐B+120元，有小點跟飲品可以搭配\n\n我有選擇障礙真的好麻煩，我想吃咖哩也想吃酸辣，但當天想吃咖哩更多一些\n\n所以點了咖哩雞肉和粉$168+A套餐$60加購越南炸雞，我真的覺得餐點很優\n\n\n咖哩雞肉河粉$168\n\n看起來超級好吃阿，裡面很多料欸，有整隻雞腿肉、丸子外\n\n還有九層塔、檸檬、辣椒、生豆芽等配料，一開始配料是分開放，在自己加進去\n\n丸子有三顆，應該是魚丸，有像在吃外面賣的咖哩魚丸的感覺，還不錯呢\n\n雞腿肉非常的軟嫩好吃，且超級多塊\n\n感覺是一整隻雞腿排下去最邊邊有雞腿的骨頭那段，最嫩的部分\n\n河粉搭配咖哩湯汁一起吃真的超棒，他咖哩真的很濃郁好喝\n\n整碗吃光光，且加入辣椒一起吃真的很棒，但檸檬我只擠一點點\n\n因為整個下去湯會變酸的，我是比較愛原味的咖哩，還好他釋放旁邊可以自己加\n\n\n越南炸雞$68(套餐價$60)\n\n然後更讓我驚豔的是這個越南炸雞，還有附特色醬料\n\n加價60元A套餐我選了炸雞，以這價位來說份量不少呢\n\n且都滿大塊的，重點也是很軟嫩，炸得剛剛好外酥內軟，朋友也大讚這個炸雞\n\n下次來新光還會想再吃這間，推薦給大家囉\n\n\n現在還在剛開幕階段，雖然錯過了前三天的買一送一優惠\n\n但到2020/5/23前，還是有單點河粉一碗送越南咖啡活動，每天限量50杯歐\n\n網誌圖文版:https://www.tony60533.com/airplane-pho", "post_vote": {"pos": 0, "neg": 0, "neu": 0}, "comments": []}