{"post_board": "Food", "post_id": "M.1603114004.A.634", "post_time": "1603114004", "post_title": "[食記] 金大鋤壽喜燒(三創店)吃到飽壽喜燒", "post_author": "jasmine1112", "post_body": "餐廳名稱：金大鋤壽喜燒(三創店)\n   消費時間：2020年/10月\n   地址：台北市中正區市民大道三段2號9樓\n   電話：02 2351 0668\n   營業時間：\n\n        週六至周日 11:00-21:00\n        周一至週五 11:00-14:00/ 17:00-20:30\n\n\n   圖文版:https://genius0509.pixnet.net/blog/post/225071373\n\n\n每次來三創都是到高麗園吃飯，每次經過金大鋤壽喜燒都以為沒啥人。\n\n但今天家人找吃飯，挑了金大鋤壽喜燒(三創店)，才發現原來這生意也不錯。\n\n整體而言，我們都覺得不錯吃，價格上也頗平價的，是可以再回訪的一間店。\n\n加上交通便利，無論是開車還是搭大眾運輸工具，都非常的方便。\n\n這天和家人約吃飯，本來想要先入座，但服務生告知先入座就會開始計算時間，\n\n所以我們等人到齊後才一起進去。\n\n平日晚餐有分Ａ套餐、Ｂ套餐、Ｃ套餐。我們選擇了Ｂ套餐，因為有牛肉。\n\nＣ套餐就是多了白蝦跟櫻桃鴨。\n\n個人不愛壽喜燒煮海鮮，也沒有特愛櫻桃鴨，所以Ｂ餐就很適合我們了。\n\n湯底的部分選擇壽喜燒。\n\n鍋底一開始就擺放洋蔥跟蔥，會先稍微乾煎一下，然後再倒入壽喜燒醬汁及水調和。\n\n所有的蔬菜食材採自助式，選擇性頗多的，肉品則用平板電腦點餐。\n\n飲料吧的選擇也很多～\n\n讓我覺得特別的是，麵的種類很多、還有刈包。\n\n當然也有提供白飯-月光米。\n\n但今天來就是只想吃肉-牛肉，所以主力不在於麵跟飯。\n\n但我們所拿的麵吃起來還不錯～\n\n飯也不賴！\n\n雞肉的選擇只有雞腿仁丁，豬則有里肌肉跟梅花豬，牛的話就是牛五花跟牛背肩。\n\n若真的要說啥缺點的話，就是肉片切的很薄，每一次上的分量也不多，\n\n所以我們一直、一直、一直加點肉。\n\n但好處是切的薄，肉涮一下就熟了。\n\n整體而言，他的肉不錯吃。\n\n但我個人偏好牛肉，特別是牛五花；可是家人比較喜歡牛背肩。\n\n豬肉也不錯吃，但還是比較愛牛肉。\n\n加點肉品在整間客滿的情況下，上菜速度不算慢。\n\n用餐時間只有一個小時半，超過最後加點的時間，平板就不能再點肉了。\n\n但服務生會親自來詢問要最後加點嗎?\n\n\n三個人開兩個鍋子，煮得還算快，時間上也算是充裕不緊迫。\n\n吃完後，大家心滿意足的說下次還可以來吃看看！", "post_vote": {"pos": 0, "neg": 0, "neu": 0}, "comments": []}