{"post_board": "Food", "post_id": "M.1606987569.A.99A", "post_time": "1606987569", "post_title": "[食記] 台中西屯 薩克森比利時餐酒館", "post_author": "gourmetism", "post_body": "餐廳名稱：薩克森比利時餐酒館\n   消費時間：2020/11\n   地址：台中市西屯區青海路二段242-13號\n   電話：(04)2708-7389\n   營業時間：17:30~1:30\n   每人平均價位：300~500\n   推薦菜色：綜合拼盤、國境之南、清涼摩奇多\n\n圖文網誌版：https://happylife698.pixnet.net/blog/post/230143591\n\n餐酒館大致可區分為兩種，以餐佐酒或以酒侍餐，薩克森當是屬於前者，和之前曾經拜訪\n\n過的Matches Bar風格挺相似的。\n\n【廣編特輯】台中西區 Matches Bar & Restaurant。人生初訪酒吧，結果還是沒喝酒\n\n餐廳鄰近逢甲商圈，隔壁的好樂迪可以用來當作地標，站在門外就能看見一整面氣勢驚人\n\n的啤酒牆。\n\n除了五彩繽紛的酒瓶，餐廳到處可見超級英雄的身影，相信漫威迷應該也是迫不及待想要\n\n來拜訪了吧XD\n\n走上二樓，鋼鐵人使出毀滅的噴射白光迎接客人。(啊！不對，這不是遊戲王XD)\n\n二樓的用餐空間將兩棟建築物打通，容納4、50人都不成問題。\n\n同時，店家還有提供投影螢幕，很適合包場開party！\n\n【溫馨小叮嚀】喝酒不開車，開車不喝酒。\n\nMenu\n\n採單點模式，餐點以義式料理為主，每人低消300元，需額外收取一成服務費。\n\n酒水品項相當驚人，除了經典調酒系列，還有各國啤酒可以選擇。\n\n蛋黃哥燻雞義大利麵 (NT. 300)\n\n超級地中海披薩 (NT. 320)\n\n屬於中型薄片披薩，用料還算豐富，包含鮮蝦、花枝、蟹肉和鯛魚片，建議趁熱食用，尤\n\n其是冷掉的鯛魚片味道真的母湯XD\n\n綜合拼盤 (NT. 380)\n\n這款炸物拼盤一口氣網羅了脆薯、薯塊、洋蔥圈、起司條、雞柳條和雞米花，份量相當有\n\n誠意，是個人心目中CP值最高的一款餐點。\n\n清涼摩奇多 (NT. 250) & 國境之南 (NT. 280)\n\n兩款調酒據說都蠻好喝的，特別是後者的色調，真的給人一種南國夏日沙灘的感覺。\n\n當然，不嗜酒的小綿羊點了一杯無酒精飲品，相較之下平凡了些。\n\n\n\n【分項評比】\n\n美味度：★★★☆\n\nCP值：★★★\n\n用餐氣氛：★★★★\n\n服務態度：★★★☆\n\n小結：\n\n這類型的餐廳講求的是氣氛，餐點反而是其次。\n\n如果你也喜歡偶爾小酌一杯，剛好又是個漫威迷，或許可以考慮來一趟薩克森喔~~~\n\n--\n歡迎追蹤小綿羊の樂活日誌~~~\n\nBlog：http://happylife698.pixnet.net/blog\n\nFacebook：https://www.facebook.com/happylife698/", "post_vote": {"pos": 1, "neg": 0, "neu": 0}, "comments": [{"type": "pos", "author": "oao88", "content": "感覺很讚"}]}