{"post_board": "Food", "post_id": "M.1589949301.A.5E0", "post_time": 1589949301, "post_title": "[請益]", "post_author": "pantani", "post_body": "1.想找的餐飲類別\n盛岡冷麵\n\n2.用餐地區\n台灣，大台北為主\n\n\n\n多年前在盛岡當地吃到冷麵\n對那種Q彈的麵條口感\n以及清新又微辣爽口的湯汁印象深刻\n可惜近年一直沒有機會再去當地用餐\n最近天氣轉熱看來今年又會是個酷暑\n讓我格外思念那個味道\n\n因此想詢問看看\n台灣是否有地方能吃到盛岡冷麵\n雖然韓式料理店有類似的\n但畢竟味道還是不同\n\n謝謝\n\n\n-----\nSent from JPTT on my Samsung SM-A730F.", "post_vote": {"pos": 1, "neg": 0, "neu": 0}, "comments": [{"type": "pos", "author": "yohoant", "content": "也想知道+1", "order": 1}]}