{"post_board": "Food", "post_id": "M.1591193964.A.2E4", "post_time": "1591193964", "post_title": "[食記] 台北市文山區木新路上-佳佳冰店", "post_author": "fatlee", "post_body": "餐廳名稱：佳佳冰店\n   消費時間：2020年/4月\n   地址： 台北市文山區木新路二段245號\n   電話： 02 2234 0230\n   營業時間：  11:30–22:00\n\n圖文網誌版: https://twpang.com.tw/blog/post/jiajia_ice_mucha\n\n\n---------------------------------------------------------\n\n\n今天放假 一樣跟母親在木柵散步 享受午後的陽光\n\n在木柵河堤散步後 …想說下午要來點甜點 於是在恆光橋附近選擇這間冰店-佳佳冰店 當\n作本次的下午茶點心\n\n\n\n\n\n四月雖然外頭有陽光照耀近來 但…空氣中還是帶著些許的寒意\n\n雖然是冰店 但看到外頭貼著熱豆花 就跟著母親來到店裡面享用餐點\n\n\n\n乾淨的櫥窗內 有著大量可口的佐料可以搭配冰品、豆花\n\n\n\n\n\n\n\n這間店強調他們的淨水器 如果對這方面有需求的朋友 可以參考一下\n\n\n\n店內 店外都有座位可以坐\n\n大家一起圍著小桌子吃冰品感覺也別有一番風味\n\n\n\n\n\n菜單部分如下\n\n\n\n首先是母親點的芋頭+花生豆花 (熱)\n\n\n\n芋頭的部分 母親表示非常喜歡 芋頭本身的口感、香味都還在  吃起來挺不錯的\n\n\n\n本胖點的芋圓+花生豆花\n\n\n\n豆花本身吃起來沒有澀澀的口感 糖水溫和不膩口 喝起來挺順的\n\n芋圓、地瓜圓沒有煮得太爛 咬下去除了可以感受到原本的可口的香味外 還有點些許QQ的\n口感在 挺不錯的\n\n\n\n\n\n由於今天有點冷 本胖跟母親兩人都吃熱的豆花 下次等天氣爆熱的時候\n\n再來享受他們家的雪花冰吧~\n\n店內有集點活動 如果喜歡吃他們家冰品、豆花的話 再來拿集點卡來蒐集優惠吧~\n\n\n\n\n\n佳佳冰店\n電話： 02 2234 0230\n地址： 台北市文山區木新路二段245號\n開放時間： 11:30–22:00\n\n\n\n\n\n--\n\n跟著賤胖在台灣吃喝玩樂的故事~\nhttps://twpang.com.tw/\n\n台灣貪吃胖臉書粉絲團 (即時發布文山新店美食)\nhttps://www.facebook.com/a12425/\n\n--\n\n\n※ fatlee:轉錄至看板 Wen-Shan                                      06/04 21:25", "post_vote": {"pos": 3, "neg": 0, "neu": 0}, "comments": [{"type": "pos", "author": "yakifone", "content": "可惜普普泡消失了"}, {"type": "pos", "author": "grumpykido", "content": "這家好吃！我之前住樓上一週吃五次！"}, {"type": "pos", "author": "bsnyyp", "content": "必點黃粉粿！"}]}