{"post_board": "Food", "post_id": "M.1587264027.A.F7C", "post_time": 1587264027, "post_title": "[食記] 台北中山 勝王 人氣排隊拉麵 5/06起休業", "post_author": "goodcutecat", "post_body": "餐廳名稱：勝王\n   消費時間：2020年/04月\n   地址：臺北市中山區中山北路一段94號 (近捷運中山站)\n   營業時間：平日 11:30-14:00、17:00-20:30；\n             假日 11:30-20:30；週四公休。\n   每人平均價位：300\n   推薦菜色：每日由粉絲專頁更新菜色\n\n   ==================================================\n\n   圖文好讀版:\n\n   https://goodcutecat.pixnet.net/blog/post/352061302\n\n   ==================================================\n\n中山站附近不愧為日系美食的一級商圈，這裡聚集了幾乎所有款式的日式料理，還有幾乎\n所有聽過的、沒聽過的拉麵。今天要吃的是拉麵名店鬼金棒...隔壁的勝王。\n\n門前的騎樓柱就貼著一個「排隊起點」的告示，也確實在開始營業前就形成了不短的人龍\n。\n\n「勝王」原本屬於鬼金棒味噌拉麵的「二毛作」，僅在每週二營業。所謂的「二毛作 (に\nもうさく)」，意旨在同一塊田地中，一年內耕種兩種作物。衍伸應用在餐飲業裡，代表\n同一間店，在午/晚餐或不同日子推出不同的菜單。\n\n\n因此，不但共用同一間店的設備、分攤店租，也能帶給消費者不一樣的新鮮感 (資料來源\n)。後來勝王於 2018 年底獨立出來，也就直接開在鬼金棒旁邊。\n\n順帶一提，勝王內部是沒有洗手間的，因此想上洗手間的，就逕自走入鬼金棒即可。店門\n口貼著顧客須知，包括:\n\n1. 低消一人一席碗麵。\n2. 不提供外帶或打包。\n3. 店內禁止攝影拍照 (除餐點外)。\n4. 家長請勿帶入不受控的孩童。\n5. 「本店是拉麵店，不是滑手機的地方，發揮你的同理心，用餐完畢儘速空出座位大家\n都能早點進來吃麵。」\n6. 「若無法認同及遵守以上事項，請勿入店消費以免造成顧客及店家彼此的困擾。」\n\n自然每間店可以在法律的範圍內自訂遊戲規則，個人忖度了一下，上述規定也很難違反\nXD 但把這些挑明寫在大門口，還是難免讓我體會到不小的壓迫感。\n\n上網搜尋了一下，原來是之前二毛作時期，發生了「解壓縮」的排隊糾紛。如此才會特別\n規定，小孩、老人或孕婦，來此均無優待。雖然我覺得也許有更圓融的處理方法，例如在\n等候區設置輕便板凳之類的，畢竟在孕期確實不耐久站。\n\n這邊照的另一個小海報，則是陳列了勝王用在拉麵裡的「七味」，有點反光看不清楚，他\n們分別是陳皮、胡麻、山椒、白薑、紫蘇、柚子與蕃椒。\n\n由於店內環境不許拍攝，簡單用文字說明一下。進門後先在自動販賣機上點選想要的餐點\n與加點項目，再投入紙鈔，印出收據交給店員；又或者可以掃描販賣機最上層的街口支付\n，輸入價錢後將手機畫面展示給店員看。我們去吃的這天，販賣機正好壞了，造成店內有\n空位、外面繼續排隊的窘境。店員修復後，才讓食客魚貫點餐後入座。\n\n而菜單因為每日更換，有時會有限定口味，故必須上臉書官方粉絲頁查看。以下菜單是我\n們當天吃的菜色種類，圖片取自粉絲頁。麵的價格帶落在 230~300 元間。\n\n點餐後坐定，面前又是標語。\n\n葡萄山椒郫縣豆瓣麻婆豆腐薩索雞白湯蕎麥 $300\n\n豐富且兼具色香味的呈現，除了橄欖油炒的麻婆豆腐外，還有前面講的七味，七種味道彼\n此間搭配組合也各自表現。\n\n雞白湯用的是薩索雞 (Sasso)，有興趣的讀者可以參考前文《VG Café》的介紹。雞白湯\n的濃醇渾厚，讓麻婆與花椒的麻、辣口感溫潤許多，是繼暖胃又過癮的操作。\n\n蕎麥細麵，口感很彈韌，是我喜歡的類型，巴湯的能力也很優。許多配料切得細碎，讓麵\n帶著一起吃也似無不可。\n\n八幡屋瑪莎拉七味薩索雞白湯蕎麥 $300\n\n往回溯勝王設計的幾套菜單，把台灣牛肉麵、蟹肉、肉骨茶等等改造成拉麵，也每天更換\n菜單，創新又創意，難怪養出死忠顧客時常造訪。這天吃的是瑪莎拉，原本沒意會過來，\n直到嚐了一口朋友的湯頭，才知道是指以前在尼泊爾吃過的 Masala，經典印度香料的總\n稱。\n\n每位師傅有自己的獨門配方，但大多都包含肉桂、肉豆蔻、黑胡椒、小荳蔻及薑等。勝王\n的版本香而不辣，與溫潤的雞白湯一起喝，更是好入喉。\n\n葡萄山椒郫縣豆瓣麻婆豆腐薩索雞白湯蕎麥 $300\n\n左看右看，我也跟朋友選了一樣的麻婆豆腐蕎麥，這張拍起來配料又更加豐富了。\n\n每碗拉麵都有一塊的厚切叉燒，相較於配料的豐富與湯頭令人驚豔的溫潤感，個人感覺叉\n燒就沒有太突出。\n\n不同於朋友的細麵，我選手揉麵，沒想到口感比細麵更韌更彈牙，咬著實在過癮。\n\n勝王可以免費加麵，加的一律是細麵，因此若一開始選擇手揉麵，就可以在一趟吃到兩種\n麵體。\n\n\n後記：\n\n從湯頭、配料到麵體，再加上頻繁推陳出新的菜色，不難理解勝王能擁有高人氣的原因。\n隔壁的壯漢用完餐後，詢問店員該把空碗放在原桌面上還是端到台上方便收拾，店員就簡\n單回了一句「隨便你呀！」...也許我們平常都習慣了服務至上的服務業環境，突然被堵\n一句還真有點不知所措。稍微翻了一下 Google 評論，看來遇到的不是個案。對我來說，\n用餐的緊繃感是強烈的，因此美好食物帶來的體驗也打了折扣。\n\n上粉絲專頁看，由於原地點要都更，勝王僅營業至2020年5月5日，之後無限期休業，直到\n找到新店面為止。想體驗的讀者可能要盡快了XD\n\n==========\n\n食物：★★★★☆\n\n氣氛：★ 壓力下吃完一碗麵。\n\n速度：★★★★\n\n服務：★ 有個性、會煮麵，與維持和陌生人交談該有的禮節應該不衝突...\n\n價位：★★★★\n\n無障礙：★★★☆ 入口及出口有小台階，洗手間需至隔壁鬼金棒使用。\n\n==========\n\n勝王\n\n臺北市中山區中山北路一段94號 (近捷運中山站)\n\n不提供訂位服務，採現場排隊制，也無法派代表排隊。\n\n營業時間：平日 11:30-14:00、17:00-20:30；假日 11:30-20:30；週四公休。\n\n--\n\n向任意門許願\n希望能有更多無障礙餐廳\n\nhttp://goodcutecat.pixnet.net/blog", "post_vote": {"pos": 19, "neg": 0, "neu": 19}, "comments": [{"type": "pos", "author": "LuciusMalfoy", "content": "推氣氛不太友善又不便宜就不想去吃了", "order": 1}, {"type": "pos", "author": "s080014", "content": "服務這樣乾脆結束營業", "order": 2}, {"type": "pos", "author": "a120463", "content": "吃飯又不是吃服務，除非有收服務費不然都還好", "order": 3}, {"type": "pos", "author": "STELLA0901", "content": "吃飯不是吃服務的,但至少不能讓吃飯的人感到壓迫或心", "order": 4}, {"type": "neu", "author": "STELLA0901", "content": "情不悅吧", "order": 5}, {"type": "pos", "author": "StarStar", "content": "服務雖不能吃，但待人接物要有基本禮儀存在的", "order": 6}, {"type": "neu", "author": "STELLA0901", "content": "花錢是吃飯,不是買不爽的", "order": 7}, {"type": "pos", "author": "zuzuk", "content": "去餐廳吃飯服務的部份本來就算滿重要的吧", "order": 8}, {"type": "neu", "author": "uranusjr", "content": "沒在現場無法定論, 但是純看文字店員在這裡的應對也還好", "order": 9}, {"type": "neu", "author": "uranusjr", "content": "沒有到畢恭畢盡但就是普通的說話啊, 回應合理也不到失禮", "order": 10}, {"type": "pos", "author": "misky1990", "content": "上次去用餐覺得服務還可以", "order": 11}, {"type": "neu", "author": "e3633577", "content": "隨便你這句應該還好吧", "order": 12}, {"type": "pos", "author": "sm0214", "content": "有緊繃嗎？還算ok的氛圍吧", "order": 13}, {"type": "neu", "author": "NouTsan", "content": "不常去或沒去過的人可能多少會有點緊張吧", "order": 14}, {"type": "neu", "author": "blue2999", "content": "是不是武漢肺炎害的啊", "order": 15}, {"type": "neu", "author": "oijkue", "content": "這間店員連最基本的接客應對都不合格", "order": 16}, {"type": "neu", "author": "oijkue", "content": "反正外面排隊這麼長,不差你一位客人", "order": 17}, {"type": "neu", "author": "oijkue", "content": "在加上排隊的時間成本,完全沒有去的價值", "order": 18}, {"type": "neu", "author": "hoyumi", "content": "去過好幾次根本沒感覺什麼無禮 很多拉麵店都這種風格", "order": 19}, {"type": "neu", "author": "hoyumi", "content": "把制定規則跟不禮貌畫上等號我也是笑了", "order": 20}, {"type": "pos", "author": "altcd", "content": "雖沒去過但看文字還好+1 先把規則定好也沒什麼特別刁難的點", "order": 21}, {"type": "pos", "author": "heloiselu", "content": "實際拜訪過，覺得服務態度不錯欸@@", "order": 22}, {"type": "pos", "author": "stepandstare", "content": "去過五次以上了，沒有覺得哪裡沒禮貌啊", "order": 23}, {"type": "pos", "author": "gaga326", "content": "去過一次沒有覺得態度不好啊！反倒覺得店家限制不能解壓", "order": 24}, {"type": "neu", "author": "gaga326", "content": "縮很棒啊XD", "order": 25}, {"type": "pos", "author": "ginsengwolf", "content": "孕期不能久站還去排隊店不是自找罪受嗎？不通。 隨便", "order": 26}, {"type": "neu", "author": "ginsengwolf", "content": "你這句確實不夠客氣，不欣賞這句。", "order": 27}, {"type": "neu", "author": "hoyumi", "content": "樓上可能不知道之前孕婦事件鬧很大", "order": 28}, {"type": "pos", "author": "KerKerKerX3", "content": "拉麵店有的規矩真的很多", "order": 29}, {"type": "neu", "author": "ginsengwolf", "content": "有印象了。孕婦自己帶椅子比較合理", "order": 30}, {"type": "pos", "author": "isdeerzi", "content": "勝王一直都滿忙的吧 這種狀況下這樣回覆不算不友善了", "order": 31}, {"type": "pos", "author": "lunadir", "content": "店家有權選擇客人，客人也有權選擇店家，如果說明文不接", "order": 32}, {"type": "neu", "author": "lunadir", "content": "待某些客人的話，其實也不用勉強，反正目標客人忠誠就好", "order": 33}, {"type": "pos", "author": "ct20100806", "content": "認證詢問拉麵店為什麼都這麼跩？跟許多老闆年輕時是8", "order": 34}, {"type": "neu", "author": "ct20100806", "content": "+9有關係嗎？", "order": 35}, {"type": "pos", "author": "sibin", "content": "推樓上，跩店真的常常都是拉麵店，這到底什麼文化", "order": 36}, {"type": "pos", "author": "graciehunter", "content": "腦內小劇場太多 拉麵店又不是餐廳", "order": 37}, {"type": "neu", "author": "hoyumi", "content": "原來不滿足客人要求等於跩店 我笑了", "order": 38}]}