{"post_board": "Food", "post_id": "M.1580646069.A.5FA", "post_time": 1580646069, "post_title": "[食記] 台中 米花KOUJI", "post_author": "z24518261", "post_body": "名稱：米花 KOUJI\n消費時間：2019 年/ 11月\n地址：400台中市中區民族路35號\n電話：04 2224 4168\n營業時間：08:00–17:00 週一休息\n價位：300\n\n\n【台中】米花KOUJI｜少見的甘糀系列飲品｜老屋新生～老宅文青餐廳｜台中火車站美食\nblog 多圖 好讀版 https://z24518261.pixnet.net/blog/post/351675652\n\n\n今天拜訪的是位於台中火車站附近的米花KOUJI，身為一個基隆人，自從去年認識了台中\n女朋友之後，台中就變成了我第二個熟悉的城市，而這個米花，對我來說是從基隆搭火車\n過來一起吃個午餐很方便的餐廳。\n\n\n老宅重新裝潢，店內走的是很簡約的日系風格，加上賣的是手工貝果、輕食、蛋糕等，綜\n觀來說，是年輕人會喜歡來的地方。\nhttps://3.share.photo.xuite.net/z24518261/13e6876/20477894/1222906800_x.jpg\n\n門口有擺放一個城市故事櫃，有一些與台中相關的活動DM。\nhttps://3.share.photo.xuite.net/z24518261/13e68d9/20477894/1222906899_x.jpg\n\n店內空間很寬敞，有提供WIFI，有一些座位還有設置插座。\nhttps://3.share.photo.xuite.net/z24518261/13e6877/20477894/1222906801_x.jpg\nhttps://3.share.photo.xuite.net/z24518261/13e68d8/20477894/1222906898_x.jpg\nhttps://3.share.photo.xuite.net/z24518261/13e683b/20477894/1222906997_x.jpg\n\n門口一進來這邊是回收區。\nhttps://3.share.photo.xuite.net/z24518261/13e689f/20477894/1222907097_x.jpg\n\n櫃台前面有很多不同口味的貝果，鹹的、甜的都有。\nhttps://3.share.photo.xuite.net/z24518261/13e68a0/20477894/1222907098_x.jpg\n\n收銀檯旁邊還有一些碗盤、小物販賣。\nhttps://3.share.photo.xuite.net/z24518261/13e6803/20477894/1222907197_x.jpg\nhttps://3.share.photo.xuite.net/z24518261/13e68d9/20477894/1222905619_x.jpg\n\n\n大家應該會很好奇「米花」這個店名是怎麼來的，\n\n\n柯南BGM請下，\n\n\n喔，沒有啦，跟柯南完全沒有關係。\n\n\n米花是日本漢字「糀」的意思，糀指的是長在米上面的麴菌，跟「麴」是一樣意思的，也\n一樣讀作KOJI，會使用在日本酒、醬油、味噌、等發酵品，而且滿營養的，在日本又被稱\n為「喝的點滴」。\n\n\n\n這是第一次來的時候，女朋友點的套餐，\n日式醬油麴雞胸套餐$250，套餐內容有：\n原味貝果\n舒肥月桂雞胸佐酵素醬油麴\n酵素乾米花＋天然果醬＋自製優格＋義式烤蔬菜\n紅茶則是可以折扣50元換其他飲料。\n\n甘米花系列的飲品大概落在70~80元左右。\nhttps://3.share.photo.xuite.net/z24518261/13e6878/20477894/1222906802_x.jpg\nhttps://3.share.photo.xuite.net/z24518261/13e683c/20477894/1222906998_x.jpg\nhttps://3.share.photo.xuite.net/z24518261/13e68ec/20477894/1222906406_x.jpg\n\n我自己是點了一杯可可甘米花，味道是滿普通的，不過底下有些許的米粒，攪拌之後帶有\n一點酒釀的風味，覺得還滿特別的。\nhttps://3.share.photo.xuite.net/z24518261/13e689e/20477894/1222905816_x.jpg\n\n\n第二次來，依舊點了可可甘米花。\nhttps://3.share.photo.xuite.net/z24518261/13e68d7/20477894/1222906897_x.jpg\n\n因為沒吃早餐所以還點了原味貝果＋火腿起司$50跟巧克力蛋糕$90。\nhttps://3.share.photo.xuite.net/z24518261/13e68eb/20477894/1222906405_x.jpg\n\n一坨優格放在蛋糕旁點綴，可以增加味道的層次，不過我女朋友說，旁邊這個優格，原本\n應該是在上面的，只是他滑下來了，吃起來是好吃，就中規中矩的一塊蛋糕，但90塊我覺\n得有點貴就是了。\nhttps://3.share.photo.xuite.net/z24518261/13e6815/20477894/1222906703_x.jpg\n\n\n貝果的話，雖然乍看之下好像是蓬鬆口感，但其實是偏向有嚼勁的。\nhttps://3.share.photo.xuite.net/z24518261/13e68ea/20477894/1222906404_x.jpg\n\n\n整體來說，我是很喜歡這間店的，因為客人很少，安靜、悠閒、不吵雜，坐落在火車站附\n近，但給人鬧中取靜的感覺，習慣了忙碌生活的人們，偶爾放下腳步，在這聊著天，看著\n人來人往的窗外，意外的，讓人覺得療癒呢。\nhttps://3.share.photo.xuite.net/z24518261/13e6804/20477894/1222907198_x.jpg\n\n--\n\n\n※ z24518261:轉錄至看板 TaichungBun                                02/02 20:21", "post_vote": {"pos": 0, "neg": 0, "neu": 0}, "comments": []}