{"post_board": "Food", "post_id": "M.1582267295.A.5BF", "post_time": 1582267295, "post_title": "[食記] 台中。努娜炸雞。逢甲夜市內小巷美食", "post_author": "twochen123", "post_body": "餐廳名稱：努娜炸雞\n   消費時間：2020年/1月\n   地址：台中市西屯區慶和街81號\n   電話：04-24527170\n   營業時間：16:30~00:00\n   每人平均價位：250~400\n   有無包廂：無\n   推薦菜色：雙拼炸雞\n\n\n---\n網誌版: https://lihi1.com/XZ6UK/ao3g6\n---\n\n\n努娜炸雞位於台中的逢甲夜市小巷尾端，人潮較少。\n\n不過旁邊有排隊美食像是波羅油、雞排等，所以還是會有多人的時候。\n\n平常逛夜市其實不太走進餐廳，因為覺得逛夜市就是要邊走邊吃小東西才有FU\n\n那天突然很想吃韓式料理，一時興起就走進去了。\n\n\n外觀上看起來還滿有韓式的時尚感。\n\nNoona查了網路才知道是韓國男生稱呼姐姐的意思，滿有趣的。\n\n當時去點餐就在討論老闆娘是不是韓國人，果然是韓國來台灣的。\n\n客人還不少，等人走一些了才拍得到比較空的樣子。\n\n\n簡單的自助區。\n\n菜單項目簡單清楚，也有韓國飲品。\n\n\n脆脆的醃蘿蔔，是每桌都有的招待小菜。\n\n味道不重，適合解膩。\n\n\n雙拼炸雞---BBQ+白雪紛飛(380)\n\n努娜的招牌是炸雞，口味非常多：\n\n原味、蒜頭醬油、紅醬、眼淚紅醬、BBQ、青蔥、白雪紛飛、香濃起司。\n\n又分成有骨與無骨，無骨的會貴一百元。\n\n而有骨炸雞的價位落在250到280之間，起司稍貴，300元。\n\n雖然菜單上其實沒有寫可以雙拼，但吃同一個口味容易膩的我還是厚顏無恥地詢問了。\n\n努娜的無骨炸雞是可以雙拼的哦！\n\n但只限定原味、紅醬、蒜頭、BBQ和白雪紛飛。\n\n我們便從中選了BBQ和白雪紛飛。\n\n\nBBQ炸雞\n\n原本以為BBQ應該不會太辣，結果這個BBQ的辣度有點小超過我和朋友可負荷的XD\n\n辣到整個人都在冒汗，後勁滿強的。\n\n因為平常不太吃辣，所以有點想放棄，卻又因為太好吃還是完食了。\n\nBBQ的醬又辣又甜鹹適中，我和朋友都很愛。\n\n非常推薦這個口味，愛吃辣的人完全可以，不愛吃辣的去買杯飲料配XD\n\n（然後我跟朋友都在討論，這個就這麼辣了，眼淚紅醬是會辣死誰啊！）\n\n我和朋友會很愛努娜的炸雞很重要的就是它的雞好嫩哦！！\n\n脆脆的皮吸附飽滿的醬，一口咬下裡面的汁流瀉出來，超Juice！\n\n\n白雪紛飛炸雞\n\n白雪紛飛是灑上起司粉。\n\n原本其實想吃軟軟的起司那種，可是不能雙拼，只好退而求其次。\n\n雞肉一樣超軟嫩，是我心中最軟嫩的一塊>///<\n\n它的起司粉意外地偏甜，我不太耐吃甜，幸好有BBQ搭，吃起來很不錯。\n\n然後就是粉滿多的小心被嗆到，哈哈。\n\n\n努娜的炸雞挺有水準，會讓人想再去試試更多不同口味。\n\n--\n\n愛玩的上班女子，也喜歡和大家分享自己的吃喝玩樂世界\n人生就是要痛快玩，用力過，歡迎參觀 :D\n\n網誌：http://andylababylove14.pixnet.net/blog\nFB：https://www.facebook.com/dearslife/", "post_vote": {"pos": 0, "neg": 0, "neu": 0}, "comments": []}