{"post_board": "Food", "post_id": "M.1592371760.A.0CD", "post_time": "1592371760", "post_title": "[食記] 宇治-中村藤吉(平等院店)", "post_author": "LeeGiKwang", "post_body": "餐廳名稱：中村藤吉(平等院店)\n   消費時間：2019年11月\n   地址：日本京都府宇治市宇治蓮華5-1\n   電話：+81 774 22 9500\n   營業時間：平日 10:30-17:00；假日 10:30-17:30\n   每人平均價位：300~800元台幣\n   可否刷卡：可\n   有無包廂：無\n   推薦菜色：抹茶類餐點\n   官網：https://www.tokichi.jp/\n-----------\n圖文網誌版：\n\nhttps://edisonisme.pixnet.net/blog/post/229490375\n-----------\n\n(圖一)\n\n這次來到宇治，有個一直朝思暮想的網紅名店「中村藤吉」，之前來\n京都時，就買過一些他們家的周邊，覺得真的滿好吃的，送禮自用兩\n相宜。\n\n所以這次不管沿途表參道上有上千家的抹茶店誘惑，我就是只想吃中\n村藤吉！不過先說結論的話：那就是吃一次就好XD\n\n交通資訊\n\n中村藤吉平等院店在平等院表參道上，宇治川旁，距JR宇治車站約700\n公尺，10分鐘步行距離；京阪線宇治車站則約450公尺，步行約6分鐘。\n\n(圖二)\n\n餐廳資訊\n\n電話：+81 774 22 9500\n\n地址：日本京都府宇治市宇治蓮華5-1\n\n營業時間：平日 10:30-17:00；假日 10:30-17:30\n\n官方網站：https://www.tokichi.jp/\n\n價位：抹茶蕎麥麵/烏龍麵 單點 990YEN\n\n(圖三)\n\n中村藤吉在宇治有兩間分店，分別是位於JR宇治站前的宇治本店和位\n於表參道的平等院店。\n\n兩間店分別從11:00和10:30開始營業，如果非中村藤吉不吃的朋友，\n建議一下車就直接進店；一方面可以避開中午吃飯排隊時間，一方面\n也可以確保餐點有最多選擇。\n\n因為我是逛完平等院，再走來平等院店候位，當時已經大排長龍了，\n我等了1個多少時才有位子，而且很多餐點都已售完。\n\n(圖四)\n\n因此料到排隊時間很長，乾脆先來宇治川沿岸走走，欣賞美麗的風景。\n\n(圖五)\n\n看看這楓紅，真的讓人醉心。\n\n又想想現在的疫情，半年前，我們真的有辦法想像，這種隨時可出國\n賞美景的日子竟是這樣的難能可貴嗎？\n\n(圖六)\n\n除了楓葉以外，連銀杏也開地放肆，對比藍天，黃色的葉子更顯地閃\n閃發亮！\n\n(圖七)\n\n算好時間回到店內，已經從1點排到2點半；早已飢腸轆轆的我，終於\n坐到位子上了。\n\n不過店員馬上說，這個沒了、那個沒了，連套餐都沒了.... ＝＝\n\n當下實在很想問他，你可以直接告訴我有什麼可以選是不是比較快...\n\n所以我只單點了生抹茶蕎麥麵。\n\n(圖八)\n\n我記得當時烏龍麵也已經完售了。\n\n(圖九)\n(圖十)\n\n其他菜單也拍給大家參考一下。\n\n記得，如果非中村藤吉不吃的話，一定要一早就來。\n\n(圖十一)\n\n除了一般的抹茶餐點以外，甜點類的抹茶當然也不能缺席囉！\n\n不過這價位真的頗驚人啊～\n\n我後來又點了一份抹茶果凍，價格跟我的蕎麥麵一樣都是990日圓。\n\n中村藤吉不只是人氣最高、排隊最長的，甚至連價位都是高人一等。\n\n(圖十二)\n\n點完餐後，先來喝杯茶吧！\n\n(圖十三)\n\n但不得不說，中村藤吉的這個茶包超級好喝！！完全有驚豔到我～\n\n所以出店後我立馬左轉從實體店鋪中購入這個茶包：）\n\n(圖十四)\n\n就是這個色澤，超美味的綠茶，不過即使單買茶包，也不太便宜，但\n個人覺得還是比坐下來吃餐點，值得多了XD\n\n(圖十五)\n\n我的位子真的非常之好，是在靠宇治川的這邊，等餐等地太無聊時，\n還可以看看河水的美景。\n\n(圖十六)\n\n印有中村藤吉本店圖樣的濕紙巾，中村藤吉本店指的是靠JR宇治站的\n那間喔！\n\n(圖十七)\n\n整間店人滿為患，但大多以觀光客為主，其中以台港韓旅客居多，超\n可怕的名氣啊！\n\n如果是日本客人的話則是以年長的族群為主，畢竟荷包比較深吧～\n\n宇治是周邊城市學生非常熱門的修業旅行地點，所以一路上你可以看\n到一堆學生，只是中村藤吉真的太貴了，店裡客人就不會看到太年輕\n的族群。\n\n(圖十八)\n\n過不了許久，我的蕎麥麵就上桌了！還好，我本來在候位時，就已經\n決定好，我就是要吃抹茶蕎麥麵了～\n\n只是很可惜的是，我本來要點的套餐沒了... 套餐還有多一碗抹茶白\n飯和小份的抹茶果凍。（殘念\n\n(圖十九)\n\n整份餐點是這樣，左邊有一份小小的漬物。\n\n右上角則是醬油、芥末和檸檬、抹茶鹽。\n\n抹茶鹽的部分可以酌量增加至醬油之中，更能增添抹茶蕎麥麵的風味。\n\n(圖二十)\n\n整份餐點吃起來相當清爽，抹茶味相當濃厚，很適合夏天，或是像今\n天這種突然回暖的秋天品嚐。\n\n而且不得不說中村家的抹茶不會讓我有種抹茶香精之感，完全是真材\n實料。\n\n但這種價位，如果還給我吃香精，我真的會生氣XDDD\n\n三兩下這份餐點就被我解決了，突然非常慶幸我有多點一份抹茶果凍，\n不然真的會懷疑我到底吃了些什麼...\n\n(圖二一)\n\n抹茶果凍！！這真的很好吃＝＝\n\n尤其是抹茶冰淇淋稍微融化一些後，直接和果凍、白玉一起吃，更好\n吃。\n\n這裡的抹茶苦大於甜，所以非常深得我心。\n\n(圖二二)\n\n如果不需要吃正餐的朋友，我更推薦來中村藤吉直接吃他們家的甜點，\n也不失為一個選擇喔！\n\n而且避開正餐時段，真的位子會好等很多；甜點的部分也比較沒這麼\n快售罄。\n\n(圖二三)\n\n最後吃飽喝足後，結帳走人，嗯！這價位，就讓各位看官自行判斷是\n否有這個價值啦～\n\n但！如果叫我下次再來排一次相同的隊，我絕對不幹！\n\n其實感覺整條表參道上的餐廳都大同小異，中村藤吉還是以吃名氣為\n主啦：）\n\n馬力歐Facebook粉絲專頁，請大家多多按讚支持^^\n\nhttps://www.facebook.com/MarioInBusan/\n\n--\n■◆◆≡──────────────────────────────────┼\n◆                                                                          │\n◆╭─╮║     ─╮│    ╭╮            ~*馬力歐X韓國X旅遊生活*~         │\n││  │├═ ╭─╯│    ╰╯         提供你最新、最即時的韓國旅遊資訊^^    │\n│╰─╯║   ╰─  │   ─┴─       https://www.facebook.com/MarioInBusan  ◆\n┼───────────────────────────────────≡▼◆", "post_vote": {"pos": 1, "neg": 0, "neu": 0}, "comments": [{"type": "pos", "author": "Parker08", "content": "去本店吃過幾樣甜點，覺得是吃過的抹茶中最好吃的"}]}