{"post_board": "Food", "post_id": "M.1578924974.A.7F6", "post_time": 1578924974, "post_title": "[食記] 新北永和-早享│心型帕里尼的方便著想", "post_author": "kielkiel", "post_body": "餐廳名稱：早享\n  地    址：新北市永和區仁愛路125號\n  電    話：02 2921 5809\n  營業時間：周二到周日7:30-15:00，周一公休\n  價    位：30-100元\n  消費日期：2019.10\n  推薦菜色：起司薯餅蛋吐司、香蕉巧克力帕尼尼、鮪魚起司厚蛋餅\n  ※食記/遊記有時效性，請以店家資訊為主。\n 　 口味屬個人感官意識，僅是記錄生活、飲食體驗，提供參考※\n\n\n=====================================================================\n\n　　[網誌圖文版：https://kielkiel.pixnet.net/blog/post/317511066 ]\n\n\n　　跟妹妹的假日瞎混時光，就是要吃早午餐啦~(一次完成兩頓餐，連進食都懶洋洋哈)\n　　會找到這間其實是漫無頭緒騎車亂逛，靠近頂溪捷運站發現這間「早享」，外觀看到\n裝潢滿精緻的，就來試看看了哈。(隨意姐妹花)\n\n　\n　\n　　方型空間環繞，座位大約25個，2-4人桌可調整拼桌。\n　　也有可觀賞街近的面窗吧台，騎樓也有兩桌。\n　　假日中午12點接近滿座。\n\n　\n　\n　　以溫暖色調的木質桌椅及地板為主風格，在櫃台區底座則貼有早期台式花磚牆。\n　　環繞的壁飾，一側是綠色植哉，一側則是人身獸頭，有些《Rusty Lake》的異色趣味\n，混搭中有協調的風格。\n\n　\n　\n　　餐具自取區。水是檸檬水。\n　\n　　早享菜單。是用像畫框一樣的木框很精緻。\n　　有吐司、厚蛋餅及帕里尼，款式都還滿有創意，價格還可以。\n　\n\n　\n　　起司薯餅蛋吐司$50 加價早餐盤$50 換奶茶加價$25\n　\n　　加價$50元可升級早餐盤附紅茶，內容每天會替換，當天會書寫在小黑板可以注意一\n下。\n　　我們那天去吃是胡麻沙拉與雞米花。\n　　生菜、玉米、黃瓜、蕃茄片很清爽新鮮，炸物也恰當好處。\n　\n\n　\n　　吐司是鮮奶吐司，柔軟Q彈有奶香，外層烤的酥酥好吃。\n　　內餡薯餅也保持剛好的外脆內軟，與柔軟的起司及蛋混合咬下，口感不錯。\n　　吐司的包裝蠻方便，可以直接抓起來吃不會用髒手。\n　　防滑隔油包裝也不會沾手油。\n　\n\n　\n　　香蕉巧克力帕尼尼 $45\n　\n　　帕尼尼形狀應該可說是「早享」賣點，是非常可愛的飽滿心型耶，就要擄獲你的心~\n　　可能因為形狀關係，比較不像一般帕尼尼容易有些太脆硬，麵包體厚實富彈性。\n　　已先對半切好，掰開即可見到填滿滿的香蕉，\n　　巧克力醬份量也給的不手軟，口味驚豔，不像一般早餐店的量販無名巧克力醬，有\nnutella巧克力醬香。\n\n　　\n　\n　　鮪魚起司厚蛋餅 $50\n　\n　　厚蛋餅吃起來較像蔥抓餅，類似外省麵館牛肉捲餅的厚度。\n　　黃金酥脆富層次口感，蛋香蔥香濃厚。\n　　鮪魚份量也不錯，每塊都能吃到指寬厚度。\n　\n\n　　\n　　整體而言，環境舒適，口味創意也不錯。\n　　內用外帶生意都很好，所以上菜時間稍久，不過早午餐本來就是悠閒閒的進食時光，\n也不著緊嘍。\n\n\n\n\n--\n\nWEb ：http://kielkiel.pixnet.net/blog\nFB：https://www.facebook.com/kielkiel0205\nIG：https://www.instagram.com/kielkiel0205/\n\n+引線木偶 Heaven tollbooth+", "post_vote": {"pos": 0, "neg": 0, "neu": 0}, "comments": []}