{"post_board": "Food", "post_id": "M.1601741310.A.6C2", "post_time": "1601741310", "post_title": "[食記] 台北 野壽司 1000元的超值午間握壽司套餐", "post_author": "kamgx58", "post_body": "餐廳名稱：野壽司\n   消費時間：2020年08月\n   店家地址：臺北市中山區吉林路22巷27號1樓\n   店家電話：02 2581 7577\n   營業時間：12：00～14：30 / 18：00～23：00（週日公休）\n   餐點價位：午間握壽司套餐1000元，干瓢卷（100元）\n   可否刷卡：可以\n   有無包廂：有\n   推薦菜色：黑鮪魚中腹，紅甘，紫海膽，牡丹蝦，干瓢卷\n   停車地點：橋下停車場\n   鄰近捷運：松江南京站，中山站\n\n   圖文網誌：https://lintzuyang79.pixnet.net/blog/post/352877573\n\n   －－－－－－－－－－－－－－－－－－－－－－－－－－－－－－－－－－\n\n   野壽司跟前一天晚上吃到的鹿羣日本料理在差不多的位置，\n\n   都是在新生北路一段跟南京東路的交口這邊，\n\n   兩間店分別位在新生北路的兩側邊。\n\n   話說這個附近的日本料理店真的很多，\n\n   隨便在google的地圖上一查，就出現有好幾十間，\n\n   真的是讓人既羨慕又忌妒，\n\n   能夠在這個競爭如此激烈的地方生存下去，\n\n   只能說野壽司真的不簡單，\n\n   或是說台北的壽司店很多都很不簡單。\n\n\n   野壽司可愛的壓巾小物\n\n   當天吃的是野壽司1000元的午間握壽司套餐，\n\n   也是野壽司的價位中最便宜一的套餐，\n\n   由於有了之前幾次台北行微踩雷的經驗，\n\n   所以現在都不敢一次就跳太多，\n\n   會想說先從基本一點的開始，\n\n   而且主要也是想試試看魚料跟醋飯的味道，\n\n   並不一定要吃到多高級的食材或是多大的份量。\n\n\n   前菜：茄子，高湯晶凍，櫻花蝦涼拌菜\n\n   雖然個人不是很喜歡茄子的味道，\n\n   不過野壽司的茄子味道不會很重，\n\n   口感上軟嫩，但是不軟爛。\n\n   高湯凍吃起來是鮮鹹味還滿重的感覺，\n\n   櫻花蝦涼菜除了比較鹹之外，不太有亮點。\n\n\n   第一貫：黑鮪魚中腹\n\n   跟記憶中的名店一樣，第一貫就直上黑鮪魚握。\n\n   野壽司的魚料熟成感很重，一吃下去就是很強烈的味道，\n\n   黑鮪魚吃起來的口感很嫩，咀嚼中可以吃得到熟成魚料的旨味，\n\n   以台北無菜單料理店的均價來說，野壽司的午餐真的很划算。\n\n\n   第二貫：紅甘\n\n   本來以為放在黑鮪魚之後紅甘吃起來的味道可能會被蓋過去，\n\n   但是，\n\n   野壽司的紅甘依舊以一種鮮味很強烈的狀態殺出，\n\n   還帶有一點脆脆的口感。\n\n   野壽司的醋飯吃起來Q彈，很有顆粒感，\n\n   溫度中間，不算太熱，但也不是冰涼的感覺。\n\n   醋飯在調味上也比較重一些，\n\n   如果不是因為魚料的鮮味也很重，\n\n   這樣強烈的醋飯很可能會把魚料味的蓋過去，\n\n   能夠這樣相得益彰也是很考驗師傅的技術跟經驗。\n\n\n   第三貫：醃漬小鯛\n\n   醋漬小鯛中間放了一些蛋鬆，吃起來會多了一些甜味，\n\n   小鯛本身有就有鮮味，不過就沒有剛剛那兩貫這麼多，\n\n   口感上主體是嫩，\n\n   但是因為有醃漬過的關係，所以還是帶有些微微的韌度。\n\n\n   第四貫：紫海膽\n\n   海膽本身的感覺很棒，鮮甜味有出來，\n\n   可是海苔的口感不太好，有點太厚跟太硬，\n\n   會影響到咀嚼這貫握壽司的融洽度。\n\n\n   第五貫：鮭魚卵\n\n   一樣是鮭魚卵的鮮鹹感讓人喜歡，可是海苔還是可惜了些，\n\n   如果可以把這兩個食材做成一個小丼飯，感覺會比較合適一些，\n\n   畢竟以海膽的口感來說是還滿細膩的食材。\n\n\n   茶碗蒸\n\n   不只是魚料的味道比較重，\n\n   蒸蛋的味道也比別人更重一些，\n\n   哈，吃起來口感很嫩，但是也不會水水的。\n\n   容器設計的很貼心，放湯匙的地方還有一個凹槽，\n\n   這樣服務人員在端的時候也比較滑來滑去。\n\n\n   第六貫：牡丹蝦\n\n   可以在1000元的握壽司之中吃到牡丹蝦，\n\n   而且還是在這種等級的壽司店之中，是還滿讓人驚訝的。\n\n   這一貫一掃剛剛兩貫海苔的不融洽，\n\n   牡丹蝦吃起來味道鮮甜，口感Q微脆，\n\n   而且也因為鮮甜味夠，\n\n   所以在味到強烈的醋飯襯托之下更顯得好吃。\n\n\n   第七貫：鰹魚 薑\n\n   魚肉吃起來嫩，\n\n   而味道很鮮或是說味道很重，\n\n   醬油醃漬過的味道很強烈，\n\n   可能不會是一般人會喜歡的味道，\n\n   對於大部分的人來說可能會覺得太鹹，\n\n   不過...平常都吃重口味的壽司羊是覺得...還不錯～～～\n\n\n   第八貫：黃雞魚\n\n   黃雞魚吃起來軟嫩，但是在味道上並不突出，\n\n   不太知道為什麼這個會放在最後一貫。\n\n\n   鐵火卷\n\n   吃起來還不錯，吃得到鮪魚的鮮甜味，\n\n   然後這樣一口一個的鐵火卷，\n\n   海苔吃起來似乎就部有這麼不合拍了。\n\n\n   細蔥卷\n\n   很純粹的細蔥，沒有其他的食材，吃起來很清，\n\n   不過也因為有這些細卷所以雖然握壽司只有八貫，\n\n   但是吃完之後是有飽足感的。\n\n\n   單點的干瓢卷（100元）\n\n   如果師傅有捲干瓢卷當成結尾，那絕對是一個升級。\n\n   如果沒有，建議大家可以點一個來吃吃看，因為真的還滿好吃的。\n\n   野壽司的干瓢吃起來有種讓人喜歡甜味，不太強烈，但是醇厚，\n\n   口感上不會太軟蛋還保有脆度，芥末也不太多，吃起來有融洽。\n\n\n   玉子燒\n\n   中間還有一顆鵪鶉蛋，\n\n   但是吃起來還是有點甜甜的味道，\n\n   淡淡的甜味配上軟軟的口感，好吃。\n\n\n   味噌湯\n\n   野壽司的味噌湯非常的鮮甜，是讓人很喜歡的味道。\n\n\n   甜點\n\n   老實說...\n\n   這個甜點的記憶點很低，\n\n   而且...\n\n   也忘記寫筆記了，\n\n   因為那天在野壽司吃飯，\n\n   竟然被旁邊的不認識的客人給出來了，\n\n   所以聊得太開心，這個甜點就...\n\n   請大家自己看圖想故事了～～～\n\n\n   感想：\n\n   補充一下野壽司的歷史，\n\n   野壽司是日本逸喜優的海外分店，\n\n   店主也是日本東西逸喜優的老闆兼店主兼師傅 荻原龍也師傅，\n\n   從網路上的資料來看野壽司應該是在2005年左右開業，\n\n   不過這也是網路上看來的資訊，不保證正確，\n\n   歷經四位板前長，\n\n   第一代板前長 藤永大介師傅，目前在日本開業，\n\n   第二代板前長 野村裕二師傅，目前是野村壽司（米其林一星）的板前長，\n\n   第三代板前長 橋本和弘師傅，目前任職於台北的「壽司芳」，\n\n   第四代板前長 佐藤隆治師傅，目前是野壽司的板前長。\n\n   野壽司的歷史不查還不會怎麼樣，一查突然覺得...\n\n   有一種查到萬神殿的感覺，並不是要神話野壽司的意思，\n\n   而是原來野壽司是一間這麼有歷史的壽司店。\n\n   也因為板前長換過不少人，\n\n   所以還是以這一次的板前長 佐藤師傅來替代這一次的野壽司吧。\n\n   佐藤師傅的魚料應該大多是有熟成過的，\n\n   所以味道都會比較重一些，魚味也會比較足，\n\n   如果平常沒有接受過比較強烈味道的刺激，\n\n   可能不會這麼習慣佐藤師傅的風格，\n\n   更不要說醋飯的味道也偏重。\n\n   或許這樣的味道會更接近日本江戶前握壽司的感覺，\n\n   而且壽司羊也覺得滿喜歡的，\n\n   至少在台北，這樣1000元的無菜單料理，\n\n   已經是很難找到競爭的對手了，\n\n   但是也很難保證會有多少人會喜歡這種味道。\n\n   因為去台北吃壽司散心也不是第一次了，\n\n   佐藤師傅的調味相對是味道比較重的，\n\n   或許也可以說是味道最重的了。\n\n   台北很多無菜單日本料理的調味都是比較輕柔，\n\n   撒上一些檸檬皮，一些酸桔的皮，再擠上檸檬汁等等，\n\n   比較像是春天或是夏天的年輕味道，\n\n   如果要說佐藤師傅的調味，會給人有一種冬天的厚重感，\n\n   這不是種貶意，而是純粹味道走向的不同。\n\n   去之前可能要先有心理準備，\n\n   這樣比較極端的味道通常不是大好就是大壞，\n\n   很難會有一種中庸的感覺。\n\n\n\n   最 後 一 樣 ， 謝 謝 大 家 看 完 ～ ～ ～", "post_vote": {"pos": 2, "neg": 0, "neu": 0}, "comments": [{"type": "pos", "author": "PeterPa", "content": "想問，假日中午也有午餐套餐嗎"}, {"type": "pos", "author": "GolfR32", "content": "感覺不錯"}]}