{"post_board": "Food", "post_id": "M.1588497644.A.CDF", "post_time": 1588497644, "post_title": "[食記] 宜蘭 大阪王將", "post_author": "osakaleo", "post_body": "餐廳名稱：大阪王將\n   消費時間：2019年1月\n   地址：宜蘭 新月廣場\n\n\n有圖有真相網誌版：https://osakaleo.pixnet.net/blog/post/352111126\n\n\n話說在日本吃過幾次大阪王將，\n但老實說，台灣的煎餃(鍋貼)和日本比起來好吃多了，\n所以在日本並不會特別想吃。\n\n會去吃大阪王將，\n大多是時間很晚沒東西吃了，就會外帶餃子回飯店吃。\n或和朋友聚餐，不想吃太貴的話，就會選大阪王將。\n\n這次在新月店吃，感想還是差不多，它的煎餃還是輸給台灣的煎餃。\n\n阿不過，它的韭菜炒豬肝，朋友很推！", "post_vote": {"pos": 0, "neg": 0, "neu": 4}, "comments": [{"type": "neu", "author": "nairod", "content": "週六本來想吃才發現三越站前店撤櫃了。刷了一下分店位置看", "order": 1}, {"type": "neu", "author": "nairod", "content": "到google 評論奇差無比，好幾間分店都是平均不到兩顆星，", "order": 2}, {"type": "neu", "author": "nairod", "content": "感覺經營管理有很大的問題，相較之下餃子的王將（京都來的", "order": 3}, {"type": "neu", "author": "nairod", "content": "那家）評價就高得多", "order": 4}]}