{"post_board": "Food", "post_id": "M.1607954356.A.A29", "post_time": "1607954356", "post_title": "[食記] 苗栗公館 陶之飲 無菜單客家料理", "post_author": "chris1225", "post_body": "餐廳名稱：陶之飲\n   消費時間：2020年/11月\n   地址：苗栗縣公館鄉成功路23號\n   電話：03-7222408\n   營業時間：週一~週日 11:00-21:00\n   推薦菜色：酸菜肉片湯.金沙豆腐.酥炸G軟骨.鮮魚燒\n\n圖文並茂無音樂你上班可以偷看版：\nhttps://caramelmm.pixnet.net/blog/post/360625784\n\n*『陶之飲』無菜單家常料理 道地客家料理 客家餐廳\n*  公館美食 公館客家餐廳 公館客家料理 苗栗無菜單料理\n\n從自然圈露營完下山的我們，尋覓到了陶之飲\n隨興撥打了電話預訂1點位置\n猶記得電話那一端人聲鼎沸\n抵達現場後真心佩服，1點還能有這樣人氣\n不愧是GOOGLE評價4.6顆心的餐廳\n\n陶之飲菜單\n陶之飲的用餐方式是無菜單料理\n每天會出的菜都不盡相同，而且只有當天知道\n份量會依據人數配給，我們一共8個人\n份量都不大，但喜歡吃多樣，所以就寫了一個\"中\"\n印象中，平均下來每個人不超過400元\n\n生意實在太好，等了超過半小時還未上一道菜...\n店家端出小菜招待，但還是好想吃正菜喔！\n\n金沙豆腐\n炸過的豆腐，酥脆金黃外衣\n包覆著水嫩內裡，咬時要小心燙口\n被炒到破碎的鹹蛋，給予適時調味\n整到餐點像炸物小品，越吃越順口\n\n蔥爆牛肉\n蔥爆牛肉是熱炒店.合菜店常有的家常菜\n原本就很有肉香味的牛肉\n經過洋蔥.蒜頭及辣椒其同爆香後\n整體滋味又更上一層樓了\n\n鮮魚燒\n本日的鮮魚燒是選用鱸魚烹煮\n採用蒸煮方式料理，將熱氣悶在其內\n僅蔥薑小辣椒輕調味，讓魚隻更能保留原汁原味\n鮮嫩的程度，需要湯匙輔助夾起，沒幾下咀嚼便能化開在嘴裡\n\n塔香鴨肉\n焦糖曼本身不太愛吃鴨肉\n不過這盤塔香鴨肉有打中我心\n鴨肉本身很嫩很嫩外，夾配薑絲幫助提味\n其中九層塔像背景音樂，默默地卻很重要\n小黃瓜讓整體口味多了明亮爽口感\n\n酥炸G軟骨\n油炸過的G軟骨，香酥美味\n有青椒．蒜頭及九層塔相佐\n像在吃鹽酥雞那樣，人人都愛，推薦必點\n\n蒜泥白肉\n這道蒜泥白肉，除了蒜泥味兒外\n還有很顯著的醋味，因為三層豬肉肥肉所占部分頗大\n所以醋味所賦予的解膩效果很好\n\n絲瓜文蛤\n除了絲瓜外，還有彩椒．菇類相伴\n喜歡絲瓜獨特的滑溜口感\n蛤蜊雖新鮮，但部分沒吐沙完全有點可惜\n就本日餐點說，這是最清爽一道菜了\n\n客家小炒\n客家小炒是當日唯一吃較不習慣的\n由洋蔥.豆干.肉絲.乾魷魚等相組成\n和市面客家小炒相比，少了芹菜外\n調味上放入不少醬油，滿鹹的就是\n\n炒時蔬\n今天的炒時蔬，印象中與過貓．高麗菜及空心菜可選\n我們選了大家都能接受的高麗菜\n意料外的這道炒時蔬滿油的，嘴唇都有油光這樣XD\n\n酸菜肉片湯\n今年冬天深深愛上酸菜白肉湯這道料理\n各家酸菜在酸度及口感上，都有各有各的特色\n這道湯頭，酸甜平衡適中，湯頭清澈\n酸菜清脆，搭配半肥半瘦的豬肉\n微涼天氣來碗熱湯，幸福感加倍\n\n『焦糖曼曼小總結』\n陶之飲的餐點平價又多樣化\n能夠吃到道地的客家料理外，且大多數的菜色調味不重\n所以對於我們外地人來說，接受度也高\n店家的招待客氣，有著滿滿人情味\n若要我說唯一缺點的話，那就是生意太好，出菜需要耐心等待\n\n\n--\n一讚一分享~\n小動作大鼓勵，感謝支持焦糖曼曼!\n\n痞客邦 http://caramelmm.pixnet.net/blog\n\n粉絲團 https://www.facebook.com/caramelmmBlog/", "post_vote": {"pos": 0, "neg": 0, "neu": 0}, "comments": []}