{"post_board": "Food", "post_id": "M.1586061052.A.E40", "post_time": 1586061052, "post_title": "[食記] 中和積穗夜市 海天宮廟口蚵仔攤", "post_author": "dong1104", "post_body": "餐廳名稱：海天宮廟口蚵仔攤\n   消費時間：2020.03\n   地址：新北市中和區民安街8-20號\n   每人平均價位：100內\n   可否刷卡：否\n   有無包廂：無\n   推薦菜色：蚵仔煎、四神湯\n\n\n好讀圖文版：https://dong1104.pixnet.net/blog/post/41594473\n\n\n這攤位於中和民安街上的廟口蚵仔攤，是一間中和積穗夜市內的人氣美食宵夜好選擇\n\n廟口蚵仔攤就位於中和海山宮的入口處，餐點有雞蛋煎、四神湯、赤肉羹、蚵仔煎、肉羹米粉/麵和炒米粉\n\n這裡的蚵仔煎味道還真是不錯，口感軟嫩，喜歡吃蚵仔煎的朋友，可以來廟口蚵仔攤試試唷！\n\n會來積穗夜市完全是因為飯店工作人員的介紹，我們從沐舍時尚酒店走過來還滿近的\n\n海天宮廟口蚵仔攤的價目表\n\n四神湯(40元/小)\n\n小腸口感相當Q彈，料多味美\n\n蚵仔煎(60元)\n\n裡面有滿滿的蚵仔和青菜，用的還是大陸妹，醬汁也很香，還帶點辣味，好吃", "post_vote": {"pos": 4, "neg": 0, "neu": 0}, "comments": [{"type": "pos", "author": "kanbruce", "content": "這家是我小時候吃到現在,好吃", "order": 1}, {"type": "pos", "author": "lindafju", "content": "這家真的不錯，附近的鹹粥的小菜很強", "order": 2}, {"type": "pos", "author": "tony77998", "content": "旁邊鹹粥炸蝦仁讚", "order": 3}, {"type": "pos", "author": "yuifish", "content": "這家跟鹹粥都超猛！！", "order": 4}]}